LICENSE.txt
evo_package_linkedin/__init__.py
evo_package_linkedin/automation/api.yaml
evo_package_linkedin/automation/entity.yaml
evo_package_linkedin/control/CLinkedinApi.py
evo_package_linkedin/control/__init__.py
evo_package_linkedin/entity/ELinkedinCompany.py
evo_package_linkedin/entity/ELinkedinInput.py
evo_package_linkedin/entity/ELinkedinOutput.py
evo_package_linkedin/entity/ELinkedinPost.py
evo_package_linkedin/entity/ELinkedinUser.py
evo_package_linkedin/entity/__init__.py
evo_package_linkedin/utility/IuLinkedin.py
evo_package_linkedin/utility/ULinkedin.py
evo_package_linkedin/utility/ULinkedinApi.py
evo_package_linkedin/utility/__init__.py
evo_package_linkedin-2024.10.22327.dist-info/LICENSE.txt
evo_package_linkedin-2024.10.22327.dist-info/METADATA
evo_package_linkedin-2024.10.22327.dist-info/WHEEL
evo_package_linkedin-2024.10.22327.dist-info/RECORD
